CHANGELOG.txt
MANIFEST.in
README.txt
setup.py
Printors/__init__.py
Simplified_JSON_DICT_LIST_printer.egg-info/PKG-INFO
Simplified_JSON_DICT_LIST_printer.egg-info/SOURCES.txt
Simplified_JSON_DICT_LIST_printer.egg-info/dependency_links.txt
Simplified_JSON_DICT_LIST_printer.egg-info/top_level.txt