Metadata-Version: 2.1
Name: Simplified-JSON-DICT-LIST-printer
Version: 0.0.1
Summary: Basic functions for printing and debugging
Home-page: UNKNOWN
Author: Peter Nguyen
Author-email: pnguyenkhang@gmail.com
License: UNKNOWN
Keywords: print
Platform: UNKNOWN
Classifier: Development Status :: 5 - Production/Stable
Classifier: Operating System :: Microsoft :: Windows :: Windows 10
